django_test_timer
